timer_py/__init__.py
timer_py/example.py
timer_py/printer.py
timer_py/timer.py
timer_py/utils.py
timer.py-2.5.0.dist-info/LICENSE
timer.py-2.5.0.dist-info/METADATA
timer.py-2.5.0.dist-info/WHEEL
timer.py-2.5.0.dist-info/top_level.txt
timer.py-2.5.0.dist-info/RECORD
