Metadata-Version: 2.1
Name: timer.py
Version: 2.5.0
Summary: Easy and accurate timer for Python.
Home-page: https://github.com/rendicahya/timer.py
Author: Randy Cahya Wihandika
Author-email: rendicahya@gmail.com
Classifier: Programming Language :: Python :: 3
Classifier: License :: OSI Approved :: GNU General Public License v3 (GPLv3)
Classifier: Operating System :: OS Independent
Requires-Python: >=3.6
License-File: LICENSE
Requires-Dist: print-color
